nbtx/__init__.py
nbtx/__main__.py
nbtx/py.typed
nbtx-0.4.0.dist-info/LICENSE.txt
nbtx-0.4.0.dist-info/METADATA
nbtx-0.4.0.dist-info/WHEEL
nbtx-0.4.0.dist-info/entry_points.txt
nbtx-0.4.0.dist-info/RECORD
