Metadata-Version: 2.3
Name: nbtx
Version: 0.4.0
Summary: Minecraft NBT parser
License: MIT License
Author: Jonas da Silva
Author-email: phoenixr41414141@gmail.com
Requires-Python: >=3.13
Classifier: Development Status :: 5 - Production/Stable
Classifier: Intended Audience :: Developers
Classifier: License :: OSI Approved :: MIT License
Classifier: Natural Language :: English
Classifier: Programming Language :: Python
Classifier: Programming Language :: Python :: 3
Classifier: Programming Language :: Python :: 3 :: Only
Classifier: Programming Language :: Python :: 3.13
Classifier: Programming Language :: Python :: 3.14
Classifier: Programming Language :: Python :: 3.15
Classifier: Topic :: File Formats
Classifier: Topic :: Games/Entertainment
Classifier: Topic :: Software Development
Classifier: Typing :: Typed
Provides-Extra: dev
Provides-Extra: docs
Requires-Dist: codespell (==2.4.1) ; extra == "dev"
Requires-Dist: coverage (==7.10.6) ; extra == "dev"
Requires-Dist: docstr-coverage (==2.3.2) ; extra == "dev"
Requires-Dist: isort (==6.0.1) ; extra == "dev"
Requires-Dist: mypy (==1.17.1) ; extra == "dev"
Requires-Dist: nox (==2025.5.1) ; extra == "dev"
Requires-Dist: pdoc (==15.0.4) ; extra == "docs"
Requires-Dist: pytest (==8.4.1) ; extra == "dev"
Requires-Dist: ruff (==0.12.12) ; extra == "dev"
Project-URL: Bug Tracker, https://github.com/phoenixr-codes/nbtx/issues
Project-URL: Documentation, https://phoenixr-codes.github.io/nbtx/nbtx.html
Project-URL: Repository, https://github.com/phoenixr-codes/nbtx
